coro_context_manager/__init__.py
coro_context_manager/py.typed
coro_context_manager-0.2.1.dist-info/LICENSE
coro_context_manager-0.2.1.dist-info/METADATA
coro_context_manager-0.2.1.dist-info/WHEEL
coro_context_manager-0.2.1.dist-info/RECORD
